[
  {
    "id": 1,
    "name": "Cody",
    "photo": "https://i.pinimg.com/236x/91/46/e9/9146e96c19fd119f7484253d5ace7d56.jpg",
    "email": "codycarson@gmail.com"
  },
  {
    "id": 2,
    "name": "Eren",
    "photo": "https://i.pinimg.com/736x/fd/b7/eb/fdb7ebb22a5ad944fcb11e4922e7d95a.jpg",
    "email": "erennoyumiya@gmail.com"
  },
  {
    "id": 3,
    "name": "Vernon",
    "photo": "https://i.pinimg.com/564x/f6/70/70/f67070597955ca4297713c01969bd099.jpg",
    "email": "theamerican@gmail.com"
  }
]